[{"symbol": "IGN1L.VS", "shortName": "Ignitis Grupe", "longName": "AB Ignitis grupe", "exchange": "LIT", "market": "vs_market", "quoteType": "EQUITY"}, {"symbol": "TEL1L.VS", "shortName": "Telia Lietuva", "longName": "Telia Lietuva, AB", "exchange": "LIT", "market": "vs_market", "quoteType": "EQUITY"}, {"symbol": "SAB1L.VS", "shortName": "Siauliu Bankas", "longName": "AB Siauliu Bankas", "exchange": "LIT", "market": "vs_market", "quoteType": "EQUITY"}, {"symbol": "LGD1L.VS", "shortName": "LITGRID", "longName": "Litgrid AB", "exchange": "LIT", "market": "vs_market", "quoteType": "EQUITY"}, {"symbol": "AMG1L.VS", "shortName": "Amber Grid", "longName": "AB Amber Grid", "exchange": "LIT", "market": "vs_market", "quoteType": "EQUITY"}, {"symbol": "IVL1L.VS", "shortName": "Invalda INVL", "longName": "Invalda INVL, AB", "exchange": "LIT", "market": "vs_market", "quoteType": "EQUITY"}, {"symbol": "LNA1L.VS", "shortName": "Linas Agro Group", "longName": "AB Linas Agro Group", "exchange": "LIT", "market": "vs_market", "quoteType": "EQUITY"}, {"symbol": "GRG1L.VS", "shortName": "Grigeo", "longName": "Grigeo AB", "exchange": "LIT", "market": "vs_market", "quoteType": "EQUITY"}, {"symbol": "AUG1L.VS", "shortName": "AUGA group", "longName": "Auga Group AB", "exchange": "LIT", "market": "vs_market", "quoteType": "EQUITY"}, {"symbol": "KNF1L.VS", "shortName": "Klaipedos Nafta", "longName": "AB Klaipedos nafta", "exchange": "LIT", "market": "vs_market", "quoteType": "EQUITY"}, {"symbol": "APG1L.VS", "shortName": "Apranga", "longName": "APB Apranga", "exchange": "LIT", "market": "vs_market", "quoteType": "EQUITY"}, {"symbol": "RSU1L.VS", "shortName": "Rokiskio Suris", "longName": "Rokiskio Suris AB", "exchange": "LIT", "market": "vs_market", "quoteType": "EQUITY"}, {"symbol": "ZMP1L.VS", "shortName": "Zemaitijos Pienas", "longName": "AB Zemaitijos pienas", "exchange": "LIT", "market": "vs_market", "quoteType": "EQUITY"}, {"symbol": "PZV1L.VS", "shortName": "Pieno Zvaigzdes", "longName": "Pieno Zvaigzdes, AB", "exchange": "LIT", "market": "vs_market", "quoteType": "EQUITY"}, {"symbol": "KNR1L.VS", "shortName": "Kauno Energija", "longName": "AB Kauno Energija", "exchange": "LIT", "market": "vs_market", "quoteType": "EQUITY"}, {"symbol": "VLP1L.VS", "shortName": "Vilkyskiu Pienine", "longName": "AB Vilkyskiu pienine", "exchange": "LIT", "market": "vs_market", "quoteType": "EQUITY"}, {"symbol": "VBL1L.VS", "shortName": "Vilniaus Baldai", "longName": "Vilniaus Baldai AB", "exchange": "LIT", "market": "vs_market", "quoteType": "EQUITY"}, {"symbol": "INC1L.VS", "shortName": "INVL Technology", "longName": "UTIB INVL Technology", "exchange": "LIT", "market": "vs_market", "quoteType": "EQUITY"}, {"symbol": "NTU1L.VS", "shortName": "Novaturas", "longName": "Novaturas AB", "exchange": "LIT", "market": "vs_market", "quoteType": "EQUITY"}, {"symbol": "INL1L.VS", "shortName": "INVL Baltic Farmland", "longName": "INVL Baltic Farmland, AB", "exchange": "LIT", "market": "vs_market", "quoteType": "EQUITY"}, {"symbol": "INR1L.VS", "shortName": "INVL Baltic Real Estate", "longName": "Special Closed-Ended Type Real Estate Investment Company INVL BALTIC REAL ESTATE", "exchange": "LIT", "market": "vs_market", "quoteType": "EQUITY"}, {"symbol": "PTR1L.VS", "shortName": "Panevezio Statybos Trestas", "longName": "AB Panevezio Statybos Trestas", "exchange": "LIT", "market": "vs_market", "quoteType": "EQUITY"}, {"symbol": "SNG1L.VS", "shortName": "Snaige", "longName": "AB Snaige", "exchange": "LIT", "market": "vs_market", "quoteType": "EQUITY"}, {"symbol": "UTR1L.VS", "shortName": "Utenos Trikotazas", "longName": "AB Utenos Trikotazas", "exchange": "LIT", "market": "vs_market", "quoteType": "EQUITY"}, {"symbol": "LNS1L.VS", "shortName": "Linas", "longName": "AB Linas", "exchange": "LIT", "market": "vs_market", "quoteType": "EQUITY"}]